README.md
setup.py
semoss/__init__.py
semoss/connection.py
semoss.egg-info/PKG-INFO
semoss.egg-info/SOURCES.txt
semoss.egg-info/dependency_links.txt
semoss.egg-info/requires.txt
semoss.egg-info/top_level.txt