Metadata-Version: 2.1
Name: semoss
Version: 1.0.3
Summary: Utility package to connect to SEMOSS instances and query data
Author: Thomas Trankle
License: MIT
